{
  "__inputs": [
    {
      "name": "DS_GRAFANACLOUD-RGORDILL-PROM",
      "label": "grafanacloud-rgordill-prom",
      "description": "",
      "type": "datasource",
      "pluginId": "prometheus",
      "pluginName": "Prometheus"
    }
  ],
  "__elements": {},
  "__requires": [
    {
      "type": "grafana",
      "id": "grafana",
      "name": "Grafana",
      "version": "12.3.0-18356121373.patch15"
    },
    {
      "type": "panel",
      "id": "piechart",
      "name": "Pie chart",
      "version": ""
    },
    {
      "type": "datasource",
      "id": "prometheus",
      "name": "Prometheus",
      "version": "1.0.0"
    },
    {
      "type": "panel",
      "id": "stat",
      "name": "Stat",
      "version": ""
    },
    {
      "type": "panel",
      "id": "state-timeline",
      "name": "State timeline",
      "version": ""
    },
    {
      "type": "panel",
      "id": "timeseries",
      "name": "Time series",
      "version": ""
    }
  ],
  "annotations": {
    "list": [
      {
        "builtIn": 1,
        "datasource": {
          "type": "datasource",
          "uid": "grafana"
        },
        "enable": true,
        "hide": true,
        "iconColor": "rgba(0, 211, 255, 1)",
        "name": "Annotations & Alerts",
        "target": {
          "limit": 100,
          "matchAny": false,
          "tags": [],
          "type": "dashboard"
        },
        "type": "dashboard"
      }
    ]
  },
  "description": "OpenTelemetry Collector otelcol-contrib hostmetrics",
  "editable": true,
  "fiscalYearStartMonth": 0,
  "graphTooltip": 1,
  "id": null,
  "links": [],
  "panels": [
    {
      "datasource": {
        "type": "prometheus",
        "uid": "${DS_GRAFANACLOUD-RGORDILL-PROM}"
      },
      "fieldConfig": {
        "defaults": {
          "color": {
            "mode": "continuous-GrYlRd"
          },
          "custom": {
            "axisPlacement": "auto",
            "fillOpacity": 70,
            "hideFrom": {
              "legend": false,
              "tooltip": false,
              "viz": false
            },
            "insertNulls": false,
            "lineWidth": 0,
            "spanNulls": false
          },
          "mappings": [
            {
              "options": {
                "0": {
                  "color": "red",
                  "index": 0,
                  "text": "down"
                },
                "1": {
                  "color": "green",
                  "index": 1,
                  "text": "up"
                }
              },
              "type": "value"
            }
          ],
          "noValue": "0",
          "thresholds": {
            "mode": "absolute",
            "steps": [
              {
                "color": "green",
                "value": 0
              }
            ]
          }
        },
        "overrides": []
      },
      "gridPos": {
        "h": 3,
        "w": 24,
        "x": 0,
        "y": 0
      },
      "id": 40,
      "options": {
        "alignValue": "left",
        "legend": {
          "displayMode": "list",
          "placement": "right",
          "showLegend": true
        },
        "mergeValues": true,
        "rowHeight": 0.9,
        "showValue": "never",
        "tooltip": {
          "hideZeros": false,
          "mode": "single",
          "sort": "none"
        }
      },
      "pluginVersion": "12.3.0-18356121373.patch15",
      "targets": [
        {
          "editorMode": "code",
          "expr": "floor(increase(system_uptime_seconds{host_name=\"$host_name\"}[1m])/59.9)",
          "interval": "",
          "legendFormat": "{{host_name}}",
          "range": true,
          "refId": "A",
          "datasource": {
            "type": "prometheus",
            "uid": "${DS_GRAFANACLOUD-RGORDILL-PROM}"
          }
        }
      ],
      "title": "System Up",
      "type": "state-timeline"
    },
    {
      "collapsed": false,
      "gridPos": {
        "h": 1,
        "w": 24,
        "x": 0,
        "y": 3
      },
      "id": 6,
      "panels": [],
      "title": "CPU",
      "type": "row"
    },
    {
      "datasource": {
        "type": "prometheus",
        "uid": "${DS_GRAFANACLOUD-RGORDILL-PROM}"
      },
      "fieldConfig": {
        "defaults": {
          "color": {
            "fixedColor": "text",
            "mode": "fixed"
          },
          "mappings": [],
          "thresholds": {
            "mode": "absolute",
            "steps": [
              {
                "color": "text",
                "value": 0
              }
            ]
          },
          "unit": "none"
        },
        "overrides": []
      },
      "gridPos": {
        "h": 6,
        "w": 3,
        "x": 0,
        "y": 4
      },
      "id": 2,
      "options": {
        "colorMode": "value",
        "graphMode": "none",
        "justifyMode": "auto",
        "orientation": "auto",
        "percentChangeColorMode": "standard",
        "reduceOptions": {
          "calcs": [
            "lastNotNull"
          ],
          "fields": "",
          "values": false
        },
        "showPercentChange": false,
        "textMode": "auto",
        "wideLayout": true
      },
      "pluginVersion": "12.3.0-18356121373.patch15",
      "targets": [
        {
          "editorMode": "code",
          "expr": "system_cpu_physical_count{host_name=\"$host_name\"}",
          "legendFormat": "__auto",
          "range": true,
          "refId": "A",
          "datasource": {
            "type": "prometheus",
            "uid": "${DS_GRAFANACLOUD-RGORDILL-PROM}"
          }
        }
      ],
      "title": "Physical CPUs",
      "type": "stat"
    },
    {
      "datasource": {
        "type": "prometheus",
        "uid": "${DS_GRAFANACLOUD-RGORDILL-PROM}"
      },
      "fieldConfig": {
        "defaults": {
          "color": {
            "fixedColor": "text",
            "mode": "fixed"
          },
          "mappings": [],
          "thresholds": {
            "mode": "absolute",
            "steps": [
              {
                "color": "text",
                "value": 0
              }
            ]
          },
          "unit": "none"
        },
        "overrides": []
      },
      "gridPos": {
        "h": 6,
        "w": 3,
        "x": 3,
        "y": 4
      },
      "id": 3,
      "options": {
        "colorMode": "value",
        "graphMode": "none",
        "justifyMode": "auto",
        "orientation": "auto",
        "percentChangeColorMode": "standard",
        "reduceOptions": {
          "calcs": [
            "lastNotNull"
          ],
          "fields": "",
          "values": false
        },
        "showPercentChange": false,
        "textMode": "auto",
        "wideLayout": true
      },
      "pluginVersion": "12.3.0-18356121373.patch15",
      "targets": [
        {
          "editorMode": "code",
          "expr": "system_cpu_logical_count{host_name=\"$host_name\"}",
          "legendFormat": "__auto",
          "range": true,
          "refId": "A",
          "datasource": {
            "type": "prometheus",
            "uid": "${DS_GRAFANACLOUD-RGORDILL-PROM}"
          }
        }
      ],
      "title": "Logical CPUs",
      "type": "stat"
    },
    {
      "datasource": {
        "type": "prometheus",
        "uid": "${DS_GRAFANACLOUD-RGORDILL-PROM}"
      },
      "fieldConfig": {
        "defaults": {
          "color": {
            "mode": "palette-classic"
          },
          "custom": {
            "axisBorderShow": false,
            "axisCenteredZero": false,
            "axisColorMode": "text",
            "axisLabel": "",
            "axisPlacement": "auto",
            "barAlignment": 0,
            "barWidthFactor": 0.6,
            "drawStyle": "line",
            "fillOpacity": 0,
            "gradientMode": "none",
            "hideFrom": {
              "legend": false,
              "tooltip": false,
              "viz": false
            },
            "insertNulls": false,
            "lineInterpolation": "linear",
            "lineWidth": 1,
            "pointSize": 5,
            "scaleDistribution": {
              "type": "linear"
            },
            "showPoints": "never",
            "showValues": false,
            "spanNulls": false,
            "stacking": {
              "group": "A",
              "mode": "normal"
            },
            "thresholdsStyle": {
              "mode": "off"
            }
          },
          "decimals": 1,
          "mappings": [],
          "thresholds": {
            "mode": "absolute",
            "steps": [
              {
                "color": "green",
                "value": 0
              }
            ]
          }
        },
        "overrides": []
      },
      "gridPos": {
        "h": 6,
        "w": 9,
        "x": 6,
        "y": 4
      },
      "id": 4,
      "options": {
        "legend": {
          "calcs": [],
          "displayMode": "list",
          "placement": "bottom",
          "showLegend": true
        },
        "tooltip": {
          "hideZeros": false,
          "mode": "multi",
          "sort": "none"
        }
      },
      "pluginVersion": "12.3.0-18356121373.patch15",
      "targets": [
        {
          "editorMode": "code",
          "expr": "sum by (state) (irate(system_cpu_time_seconds_total{host_name=\"$host_name\",state!=\"idle\"}[$__rate_interval]))",
          "legendFormat": "__auto",
          "range": true,
          "refId": "A",
          "datasource": {
            "type": "prometheus",
            "uid": "${DS_GRAFANACLOUD-RGORDILL-PROM}"
          }
        }
      ],
      "title": "CPU Time (stacked, no idle)",
      "type": "timeseries"
    },
    {
      "datasource": {
        "type": "prometheus",
        "uid": "${DS_GRAFANACLOUD-RGORDILL-PROM}"
      },
      "fieldConfig": {
        "defaults": {
          "color": {
            "mode": "palette-classic"
          },
          "custom": {
            "axisBorderShow": false,
            "axisCenteredZero": false,
            "axisColorMode": "text",
            "axisLabel": "",
            "axisPlacement": "auto",
            "barAlignment": 0,
            "barWidthFactor": 0.6,
            "drawStyle": "line",
            "fillOpacity": 0,
            "gradientMode": "none",
            "hideFrom": {
              "legend": false,
              "tooltip": false,
              "viz": false
            },
            "insertNulls": false,
            "lineInterpolation": "linear",
            "lineWidth": 1,
            "pointSize": 5,
            "scaleDistribution": {
              "type": "linear"
            },
            "showPoints": "never",
            "showValues": false,
            "spanNulls": false,
            "stacking": {
              "group": "A",
              "mode": "normal"
            },
            "thresholdsStyle": {
              "mode": "off"
            }
          },
          "decimals": 1,
          "mappings": [],
          "thresholds": {
            "mode": "absolute",
            "steps": [
              {
                "color": "green",
                "value": 0
              }
            ]
          }
        },
        "overrides": []
      },
      "gridPos": {
        "h": 6,
        "w": 9,
        "x": 15,
        "y": 4
      },
      "id": 5,
      "options": {
        "legend": {
          "calcs": [],
          "displayMode": "list",
          "placement": "bottom",
          "showLegend": true
        },
        "tooltip": {
          "hideZeros": false,
          "mode": "multi",
          "sort": "none"
        }
      },
      "pluginVersion": "12.3.0-18356121373.patch15",
      "targets": [
        {
          "editorMode": "code",
          "expr": "sum by (state) (system_cpu_utilization_ratio{host_name=\"$host_name\",state!=\"idle\"})",
          "legendFormat": "__auto",
          "range": true,
          "refId": "A",
          "datasource": {
            "type": "prometheus",
            "uid": "${DS_GRAFANACLOUD-RGORDILL-PROM}"
          }
        }
      ],
      "title": "CPU Utilization (stacked, no idle)",
      "type": "timeseries"
    },
    {
      "collapsed": false,
      "gridPos": {
        "h": 1,
        "w": 24,
        "x": 0,
        "y": 10
      },
      "id": 7,
      "panels": [],
      "title": "Memory",
      "type": "row"
    },
    {
      "datasource": {
        "type": "prometheus",
        "uid": "${DS_GRAFANACLOUD-RGORDILL-PROM}"
      },
      "fieldConfig": {
        "defaults": {
          "color": {
            "fixedColor": "text",
            "mode": "fixed"
          },
          "mappings": [],
          "thresholds": {
            "mode": "absolute",
            "steps": [
              {
                "color": "text",
                "value": 0
              }
            ]
          },
          "unit": "bytes"
        },
        "overrides": []
      },
      "gridPos": {
        "h": 6,
        "w": 3,
        "x": 0,
        "y": 11
      },
      "id": 8,
      "options": {
        "colorMode": "value",
        "graphMode": "none",
        "justifyMode": "auto",
        "orientation": "auto",
        "percentChangeColorMode": "standard",
        "reduceOptions": {
          "calcs": [
            "lastNotNull"
          ],
          "fields": "",
          "values": false
        },
        "showPercentChange": false,
        "textMode": "auto",
        "wideLayout": true
      },
      "pluginVersion": "12.3.0-18356121373.patch15",
      "targets": [
        {
          "editorMode": "code",
          "expr": "system_memory_limit_bytes{host_name=\"$host_name\"}",
          "legendFormat": "__auto",
          "range": true,
          "refId": "A",
          "datasource": {
            "type": "prometheus",
            "uid": "${DS_GRAFANACLOUD-RGORDILL-PROM}"
          }
        }
      ],
      "title": "Memory Limit",
      "type": "stat"
    },
    {
      "datasource": {
        "type": "prometheus",
        "uid": "${DS_GRAFANACLOUD-RGORDILL-PROM}"
      },
      "fieldConfig": {
        "defaults": {
          "color": {
            "fixedColor": "text",
            "mode": "fixed"
          },
          "mappings": [],
          "thresholds": {
            "mode": "absolute",
            "steps": [
              {
                "color": "text",
                "value": 0
              }
            ]
          },
          "unit": "bytes"
        },
        "overrides": []
      },
      "gridPos": {
        "h": 6,
        "w": 3,
        "x": 3,
        "y": 11
      },
      "id": 9,
      "options": {
        "colorMode": "value",
        "graphMode": "none",
        "justifyMode": "auto",
        "orientation": "auto",
        "percentChangeColorMode": "standard",
        "reduceOptions": {
          "calcs": [
            "lastNotNull"
          ],
          "fields": "",
          "values": false
        },
        "showPercentChange": false,
        "textMode": "auto",
        "wideLayout": true
      },
      "pluginVersion": "12.3.0-18356121373.patch15",
      "targets": [
        {
          "editorMode": "code",
          "expr": "system_memory_page_size_bytes{host_name=\"$host_name\"}",
          "legendFormat": "__auto",
          "range": true,
          "refId": "A",
          "datasource": {
            "type": "prometheus",
            "uid": "${DS_GRAFANACLOUD-RGORDILL-PROM}"
          }
        }
      ],
      "title": "Page Size",
      "type": "stat"
    },
    {
      "datasource": {
        "type": "prometheus",
        "uid": "${DS_GRAFANACLOUD-RGORDILL-PROM}"
      },
      "fieldConfig": {
        "defaults": {
          "color": {
            "mode": "palette-classic"
          },
          "custom": {
            "axisBorderShow": false,
            "axisCenteredZero": false,
            "axisColorMode": "text",
            "axisLabel": "",
            "axisPlacement": "auto",
            "barAlignment": 0,
            "barWidthFactor": 0.6,
            "drawStyle": "line",
            "fillOpacity": 0,
            "gradientMode": "none",
            "hideFrom": {
              "legend": false,
              "tooltip": false,
              "viz": false
            },
            "insertNulls": false,
            "lineInterpolation": "linear",
            "lineWidth": 1,
            "pointSize": 5,
            "scaleDistribution": {
              "type": "linear"
            },
            "showPoints": "never",
            "showValues": false,
            "spanNulls": false,
            "stacking": {
              "group": "A",
              "mode": "none"
            },
            "thresholdsStyle": {
              "mode": "off"
            }
          },
          "decimals": 1,
          "mappings": [],
          "thresholds": {
            "mode": "absolute",
            "steps": [
              {
                "color": "green",
                "value": 0
              }
            ]
          },
          "unit": "bytes"
        },
        "overrides": []
      },
      "gridPos": {
        "h": 6,
        "w": 7,
        "x": 6,
        "y": 11
      },
      "id": 10,
      "options": {
        "legend": {
          "calcs": [],
          "displayMode": "list",
          "placement": "bottom",
          "showLegend": true
        },
        "tooltip": {
          "hideZeros": false,
          "mode": "multi",
          "sort": "none"
        }
      },
      "pluginVersion": "12.3.0-18356121373.patch15",
      "targets": [
        {
          "editorMode": "code",
          "expr": "sum by (state) (system_memory_usage_bytes{host_name=\"$host_name\"})",
          "legendFormat": "__auto",
          "range": true,
          "refId": "A",
          "datasource": {
            "type": "prometheus",
            "uid": "${DS_GRAFANACLOUD-RGORDILL-PROM}"
          }
        }
      ],
      "title": "Memory Usage",
      "type": "timeseries"
    },
    {
      "datasource": {
        "type": "prometheus",
        "uid": "${DS_GRAFANACLOUD-RGORDILL-PROM}"
      },
      "fieldConfig": {
        "defaults": {
          "color": {
            "mode": "palette-classic"
          },
          "custom": {
            "hideFrom": {
              "legend": false,
              "tooltip": false,
              "viz": false
            }
          },
          "mappings": [],
          "unit": "bytes"
        },
        "overrides": []
      },
      "gridPos": {
        "h": 6,
        "w": 5,
        "x": 13,
        "y": 11
      },
      "id": 11,
      "options": {
        "displayLabels": [],
        "legend": {
          "displayMode": "list",
          "placement": "right",
          "showLegend": true,
          "values": [
            "percent"
          ]
        },
        "pieType": "donut",
        "reduceOptions": {
          "calcs": [
            "lastNotNull"
          ],
          "fields": "",
          "values": false
        },
        "sort": "desc",
        "tooltip": {
          "hideZeros": false,
          "mode": "none",
          "sort": "none"
        }
      },
      "pluginVersion": "12.3.0-18356121373.patch15",
      "targets": [
        {
          "editorMode": "code",
          "expr": "system_memory_utilization_ratio{host_name=\"$host_name\"}",
          "interval": "",
          "legendFormat": "{{state}}",
          "range": true,
          "refId": "A",
          "datasource": {
            "type": "prometheus",
            "uid": "${DS_GRAFANACLOUD-RGORDILL-PROM}"
          }
        }
      ],
      "title": "Memory Utilization",
      "type": "piechart"
    },
    {
      "datasource": {
        "type": "prometheus",
        "uid": "${DS_GRAFANACLOUD-RGORDILL-PROM}"
      },
      "fieldConfig": {
        "defaults": {
          "color": {
            "fixedColor": "text",
            "mode": "fixed"
          },
          "mappings": [],
          "thresholds": {
            "mode": "absolute",
            "steps": [
              {
                "color": "text",
                "value": 0
              }
            ]
          },
          "unit": "bytes"
        },
        "overrides": []
      },
      "gridPos": {
        "h": 6,
        "w": 3,
        "x": 18,
        "y": 11
      },
      "id": 12,
      "options": {
        "colorMode": "value",
        "graphMode": "none",
        "justifyMode": "auto",
        "orientation": "auto",
        "percentChangeColorMode": "standard",
        "reduceOptions": {
          "calcs": [
            "lastNotNull"
          ],
          "fields": "",
          "values": false
        },
        "showPercentChange": false,
        "textMode": "auto",
        "wideLayout": true
      },
      "pluginVersion": "12.3.0-18356121373.patch15",
      "targets": [
        {
          "editorMode": "code",
          "expr": "system_linux_memory_available_bytes{host_name=\"$host_name\"}",
          "legendFormat": "__auto",
          "range": true,
          "refId": "A",
          "datasource": {
            "type": "prometheus",
            "uid": "${DS_GRAFANACLOUD-RGORDILL-PROM}"
          }
        }
      ],
      "title": "Memory Available",
      "type": "stat"
    },
    {
      "datasource": {
        "type": "prometheus",
        "uid": "${DS_GRAFANACLOUD-RGORDILL-PROM}"
      },
      "fieldConfig": {
        "defaults": {
          "color": {
            "fixedColor": "text",
            "mode": "fixed"
          },
          "mappings": [],
          "thresholds": {
            "mode": "absolute",
            "steps": [
              {
                "color": "text",
                "value": 0
              }
            ]
          },
          "unit": "bytes"
        },
        "overrides": []
      },
      "gridPos": {
        "h": 6,
        "w": 3,
        "x": 21,
        "y": 11
      },
      "id": 13,
      "options": {
        "colorMode": "value",
        "graphMode": "none",
        "justifyMode": "auto",
        "orientation": "auto",
        "percentChangeColorMode": "standard",
        "reduceOptions": {
          "calcs": [
            "lastNotNull"
          ],
          "fields": "",
          "values": false
        },
        "showPercentChange": false,
        "textMode": "auto",
        "wideLayout": true
      },
      "pluginVersion": "12.3.0-18356121373.patch15",
      "targets": [
        {
          "editorMode": "code",
          "expr": "system_linux_memory_dirty_bytes{host_name=\"$host_name\"}",
          "legendFormat": "__auto",
          "range": true,
          "refId": "A",
          "datasource": {
            "type": "prometheus",
            "uid": "${DS_GRAFANACLOUD-RGORDILL-PROM}"
          }
        }
      ],
      "title": "Memory Dirty",
      "type": "stat"
    },
    {
      "collapsed": false,
      "gridPos": {
        "h": 1,
        "w": 24,
        "x": 0,
        "y": 17
      },
      "id": 14,
      "panels": [],
      "title": "Network",
      "type": "row"
    },
    {
      "datasource": {
        "type": "prometheus",
        "uid": "${DS_GRAFANACLOUD-RGORDILL-PROM}"
      },
      "fieldConfig": {
        "defaults": {
          "color": {
            "mode": "palette-classic"
          },
          "custom": {
            "axisBorderShow": false,
            "axisCenteredZero": false,
            "axisColorMode": "text",
            "axisLabel": "",
            "axisPlacement": "auto",
            "barAlignment": 0,
            "barWidthFactor": 0.6,
            "drawStyle": "line",
            "fillOpacity": 0,
            "gradientMode": "none",
            "hideFrom": {
              "legend": false,
              "tooltip": false,
              "viz": false
            },
            "insertNulls": false,
            "lineInterpolation": "linear",
            "lineWidth": 1,
            "pointSize": 5,
            "scaleDistribution": {
              "type": "linear"
            },
            "showPoints": "never",
            "showValues": false,
            "spanNulls": false,
            "stacking": {
              "group": "A",
              "mode": "none"
            },
            "thresholdsStyle": {
              "mode": "off"
            }
          },
          "mappings": [],
          "thresholds": {
            "mode": "absolute",
            "steps": [
              {
                "color": "green",
                "value": 0
              }
            ]
          },
          "unit": "none"
        },
        "overrides": []
      },
      "gridPos": {
        "h": 6,
        "w": 12,
        "x": 0,
        "y": 18
      },
      "id": 15,
      "options": {
        "legend": {
          "calcs": [],
          "displayMode": "list",
          "placement": "bottom",
          "showLegend": true
        },
        "tooltip": {
          "hideZeros": true,
          "mode": "multi",
          "sort": "none"
        }
      },
      "pluginVersion": "12.3.0-18356121373.patch15",
      "targets": [
        {
          "editorMode": "code",
          "expr": "sum by (state) (system_network_connections{host_name=\"$host_name\"})",
          "legendFormat": "__auto",
          "range": true,
          "refId": "A",
          "datasource": {
            "type": "prometheus",
            "uid": "${DS_GRAFANACLOUD-RGORDILL-PROM}"
          }
        }
      ],
      "title": "Network Connections",
      "type": "timeseries"
    },
    {
      "datasource": {
        "type": "prometheus",
        "uid": "${DS_GRAFANACLOUD-RGORDILL-PROM}"
      },
      "fieldConfig": {
        "defaults": {
          "color": {
            "mode": "palette-classic"
          },
          "custom": {
            "axisBorderShow": false,
            "axisCenteredZero": false,
            "axisColorMode": "text",
            "axisLabel": "",
            "axisPlacement": "auto",
            "barAlignment": 0,
            "barWidthFactor": 0.6,
            "drawStyle": "line",
            "fillOpacity": 0,
            "gradientMode": "none",
            "hideFrom": {
              "legend": false,
              "tooltip": false,
              "viz": false
            },
            "insertNulls": false,
            "lineInterpolation": "linear",
            "lineWidth": 1,
            "pointSize": 5,
            "scaleDistribution": {
              "type": "linear"
            },
            "showPoints": "never",
            "showValues": false,
            "spanNulls": false,
            "stacking": {
              "group": "A",
              "mode": "none"
            },
            "thresholdsStyle": {
              "mode": "area"
            }
          },
          "fieldMinMax": false,
          "mappings": [],
          "thresholds": {
            "mode": "percentage",
            "steps": [
              {
                "color": "green",
                "value": 0
              },
              {
                "color": "#EAB839",
                "value": 80
              },
              {
                "color": "dark-red",
                "value": 90
              }
            ]
          },
          "unit": "none"
        },
        "overrides": []
      },
      "gridPos": {
        "h": 6,
        "w": 12,
        "x": 12,
        "y": 18
      },
      "id": 24,
      "options": {
        "legend": {
          "calcs": [],
          "displayMode": "list",
          "placement": "bottom",
          "showLegend": true
        },
        "tooltip": {
          "hideZeros": true,
          "mode": "multi",
          "sort": "none"
        }
      },
      "pluginVersion": "12.3.0-18356121373.patch15",
      "targets": [
        {
          "editorMode": "code",
          "expr": "system_network_conntrack_count{host_name=\"$host_name\"}",
          "legendFormat": "Count",
          "range": true,
          "refId": "A",
          "datasource": {
            "type": "prometheus",
            "uid": "${DS_GRAFANACLOUD-RGORDILL-PROM}"
          }
        },
        {
          "datasource": {
            "type": "prometheus",
            "uid": "${DS_GRAFANACLOUD-RGORDILL-PROM}"
          },
          "editorMode": "code",
          "expr": "system_network_conntrack_max{host_name=\"$host_name\"}",
          "hide": false,
          "instant": false,
          "legendFormat": "Max",
          "range": true,
          "refId": "B"
        }
      ],
      "title": "Conntrack",
      "transformations": [
        {
          "id": "configFromData",
          "options": {
            "applyTo": {
              "id": "byName",
              "options": "Count"
            },
            "configRefId": "B",
            "mappings": []
          }
        }
      ],
      "type": "timeseries"
    },
    {
      "datasource": {
        "type": "prometheus",
        "uid": "${DS_GRAFANACLOUD-RGORDILL-PROM}"
      },
      "fieldConfig": {
        "defaults": {
          "color": {
            "mode": "palette-classic"
          },
          "custom": {
            "axisBorderShow": false,
            "axisCenteredZero": false,
            "axisColorMode": "text",
            "axisLabel": "",
            "axisPlacement": "auto",
            "barAlignment": 0,
            "barWidthFactor": 0.6,
            "drawStyle": "line",
            "fillOpacity": 0,
            "gradientMode": "none",
            "hideFrom": {
              "legend": false,
              "tooltip": false,
              "viz": false
            },
            "insertNulls": false,
            "lineInterpolation": "linear",
            "lineWidth": 1,
            "pointSize": 5,
            "scaleDistribution": {
              "type": "linear"
            },
            "showPoints": "never",
            "showValues": false,
            "spanNulls": false,
            "stacking": {
              "group": "A",
              "mode": "none"
            },
            "thresholdsStyle": {
              "mode": "off"
            }
          },
          "decimals": 1,
          "mappings": [],
          "thresholds": {
            "mode": "absolute",
            "steps": [
              {
                "color": "green",
                "value": 0
              }
            ]
          },
          "unit": "none"
        },
        "overrides": []
      },
      "gridPos": {
        "h": 6,
        "w": 6,
        "x": 0,
        "y": 24
      },
      "id": 16,
      "options": {
        "legend": {
          "calcs": [],
          "displayMode": "list",
          "placement": "bottom",
          "showLegend": true
        },
        "tooltip": {
          "hideZeros": true,
          "mode": "multi",
          "sort": "none"
        }
      },
      "pluginVersion": "12.3.0-18356121373.patch15",
      "targets": [
        {
          "editorMode": "code",
          "expr": "irate(system_network_packets_total{host_name=\"$host_name\",direction=\"transmit\",device!~\"lo|ovs-system\"}[$__rate_interval])",
          "legendFormat": "{{device}}",
          "range": true,
          "refId": "A",
          "datasource": {
            "type": "prometheus",
            "uid": "${DS_GRAFANACLOUD-RGORDILL-PROM}"
          }
        }
      ],
      "title": "Packet Transmit",
      "type": "timeseries"
    },
    {
      "datasource": {
        "type": "prometheus",
        "uid": "${DS_GRAFANACLOUD-RGORDILL-PROM}"
      },
      "fieldConfig": {
        "defaults": {
          "color": {
            "mode": "palette-classic"
          },
          "custom": {
            "axisBorderShow": false,
            "axisCenteredZero": false,
            "axisColorMode": "text",
            "axisLabel": "",
            "axisPlacement": "auto",
            "barAlignment": 0,
            "barWidthFactor": 0.6,
            "drawStyle": "line",
            "fillOpacity": 0,
            "gradientMode": "none",
            "hideFrom": {
              "legend": false,
              "tooltip": false,
              "viz": false
            },
            "insertNulls": false,
            "lineInterpolation": "linear",
            "lineWidth": 1,
            "pointSize": 5,
            "scaleDistribution": {
              "type": "linear"
            },
            "showPoints": "never",
            "showValues": false,
            "spanNulls": false,
            "stacking": {
              "group": "A",
              "mode": "none"
            },
            "thresholdsStyle": {
              "mode": "off"
            }
          },
          "decimals": 1,
          "mappings": [],
          "thresholds": {
            "mode": "absolute",
            "steps": [
              {
                "color": "green",
                "value": 0
              }
            ]
          },
          "unit": "none"
        },
        "overrides": []
      },
      "gridPos": {
        "h": 6,
        "w": 6,
        "x": 6,
        "y": 24
      },
      "id": 17,
      "options": {
        "legend": {
          "calcs": [],
          "displayMode": "list",
          "placement": "bottom",
          "showLegend": true
        },
        "tooltip": {
          "hideZeros": true,
          "mode": "multi",
          "sort": "none"
        }
      },
      "pluginVersion": "12.3.0-18356121373.patch15",
      "targets": [
        {
          "editorMode": "code",
          "expr": "irate(system_network_packets_total{host_name=\"$host_name\",direction=\"receive\",device!~\"lo|ovs-system\"}[$__rate_interval])",
          "legendFormat": "{{device}}",
          "range": true,
          "refId": "A",
          "datasource": {
            "type": "prometheus",
            "uid": "${DS_GRAFANACLOUD-RGORDILL-PROM}"
          }
        }
      ],
      "title": "Packet Receive",
      "type": "timeseries"
    },
    {
      "datasource": {
        "type": "prometheus",
        "uid": "${DS_GRAFANACLOUD-RGORDILL-PROM}"
      },
      "fieldConfig": {
        "defaults": {
          "color": {
            "mode": "palette-classic"
          },
          "custom": {
            "axisBorderShow": false,
            "axisCenteredZero": false,
            "axisColorMode": "text",
            "axisLabel": "",
            "axisPlacement": "auto",
            "barAlignment": 0,
            "barWidthFactor": 0.6,
            "drawStyle": "line",
            "fillOpacity": 0,
            "gradientMode": "none",
            "hideFrom": {
              "legend": false,
              "tooltip": false,
              "viz": false
            },
            "insertNulls": false,
            "lineInterpolation": "linear",
            "lineWidth": 1,
            "pointSize": 5,
            "scaleDistribution": {
              "type": "linear"
            },
            "showPoints": "never",
            "showValues": false,
            "spanNulls": false,
            "stacking": {
              "group": "A",
              "mode": "none"
            },
            "thresholdsStyle": {
              "mode": "off"
            }
          },
          "mappings": [],
          "thresholds": {
            "mode": "absolute",
            "steps": [
              {
                "color": "green",
                "value": 0
              }
            ]
          },
          "unit": "bytes"
        },
        "overrides": []
      },
      "gridPos": {
        "h": 6,
        "w": 6,
        "x": 12,
        "y": 24
      },
      "id": 18,
      "options": {
        "legend": {
          "calcs": [],
          "displayMode": "list",
          "placement": "bottom",
          "showLegend": true
        },
        "tooltip": {
          "hideZeros": true,
          "mode": "multi",
          "sort": "none"
        }
      },
      "pluginVersion": "12.3.0-18356121373.patch15",
      "targets": [
        {
          "editorMode": "code",
          "expr": "irate(system_network_io_bytes_total{host_name=\"$host_name\",direction=\"transmit\",device!~\"lo|ovs-system\"}[$__rate_interval])",
          "legendFormat": "{{device}}",
          "range": true,
          "refId": "A",
          "datasource": {
            "type": "prometheus",
            "uid": "${DS_GRAFANACLOUD-RGORDILL-PROM}"
          }
        }
      ],
      "title": "Bytes Transmit",
      "type": "timeseries"
    },
    {
      "datasource": {
        "type": "prometheus",
        "uid": "${DS_GRAFANACLOUD-RGORDILL-PROM}"
      },
      "fieldConfig": {
        "defaults": {
          "color": {
            "mode": "palette-classic"
          },
          "custom": {
            "axisBorderShow": false,
            "axisCenteredZero": false,
            "axisColorMode": "text",
            "axisLabel": "",
            "axisPlacement": "auto",
            "barAlignment": 0,
            "barWidthFactor": 0.6,
            "drawStyle": "line",
            "fillOpacity": 0,
            "gradientMode": "none",
            "hideFrom": {
              "legend": false,
              "tooltip": false,
              "viz": false
            },
            "insertNulls": false,
            "lineInterpolation": "linear",
            "lineWidth": 1,
            "pointSize": 5,
            "scaleDistribution": {
              "type": "linear"
            },
            "showPoints": "never",
            "showValues": false,
            "spanNulls": false,
            "stacking": {
              "group": "A",
              "mode": "none"
            },
            "thresholdsStyle": {
              "mode": "off"
            }
          },
          "mappings": [],
          "thresholds": {
            "mode": "absolute",
            "steps": [
              {
                "color": "green",
                "value": 0
              }
            ]
          },
          "unit": "bytes"
        },
        "overrides": []
      },
      "gridPos": {
        "h": 6,
        "w": 6,
        "x": 18,
        "y": 24
      },
      "id": 19,
      "options": {
        "legend": {
          "calcs": [],
          "displayMode": "list",
          "placement": "bottom",
          "showLegend": true
        },
        "tooltip": {
          "hideZeros": true,
          "mode": "multi",
          "sort": "none"
        }
      },
      "pluginVersion": "12.3.0-18356121373.patch15",
      "targets": [
        {
          "editorMode": "code",
          "expr": "irate(system_network_io_bytes_total{host_name=\"$host_name\",direction=\"receive\",device!~\"lo|ovs-system\"}[$__rate_interval])",
          "legendFormat": "{{device}}",
          "range": true,
          "refId": "A",
          "datasource": {
            "type": "prometheus",
            "uid": "${DS_GRAFANACLOUD-RGORDILL-PROM}"
          }
        }
      ],
      "title": "Bytes Receive",
      "type": "timeseries"
    },
    {
      "datasource": {
        "type": "prometheus",
        "uid": "${DS_GRAFANACLOUD-RGORDILL-PROM}"
      },
      "fieldConfig": {
        "defaults": {
          "color": {
            "mode": "palette-classic"
          },
          "custom": {
            "axisBorderShow": false,
            "axisCenteredZero": false,
            "axisColorMode": "text",
            "axisLabel": "",
            "axisPlacement": "auto",
            "barAlignment": 0,
            "barWidthFactor": 0.6,
            "drawStyle": "line",
            "fillOpacity": 0,
            "gradientMode": "none",
            "hideFrom": {
              "legend": false,
              "tooltip": false,
              "viz": false
            },
            "insertNulls": false,
            "lineInterpolation": "linear",
            "lineWidth": 1,
            "pointSize": 5,
            "scaleDistribution": {
              "type": "linear"
            },
            "showPoints": "never",
            "showValues": false,
            "spanNulls": false,
            "stacking": {
              "group": "A",
              "mode": "none"
            },
            "thresholdsStyle": {
              "mode": "off"
            }
          },
          "decimals": 1,
          "mappings": [],
          "thresholds": {
            "mode": "absolute",
            "steps": [
              {
                "color": "green",
                "value": 0
              }
            ]
          },
          "unit": "none"
        },
        "overrides": []
      },
      "gridPos": {
        "h": 6,
        "w": 6,
        "x": 0,
        "y": 30
      },
      "id": 20,
      "options": {
        "legend": {
          "calcs": [],
          "displayMode": "list",
          "placement": "bottom",
          "showLegend": true
        },
        "tooltip": {
          "hideZeros": true,
          "mode": "multi",
          "sort": "none"
        }
      },
      "pluginVersion": "12.3.0-18356121373.patch15",
      "targets": [
        {
          "editorMode": "code",
          "expr": "irate(system_network_dropped_total{host_name=\"$host_name\",direction=\"transmit\",device!~\"lo|ovs-system\"}[$__rate_interval])",
          "legendFormat": "{{device}}",
          "range": true,
          "refId": "A",
          "datasource": {
            "type": "prometheus",
            "uid": "${DS_GRAFANACLOUD-RGORDILL-PROM}"
          }
        }
      ],
      "title": "Packet Transmit Dropped",
      "type": "timeseries"
    },
    {
      "datasource": {
        "type": "prometheus",
        "uid": "${DS_GRAFANACLOUD-RGORDILL-PROM}"
      },
      "fieldConfig": {
        "defaults": {
          "color": {
            "mode": "palette-classic"
          },
          "custom": {
            "axisBorderShow": false,
            "axisCenteredZero": false,
            "axisColorMode": "text",
            "axisLabel": "",
            "axisPlacement": "auto",
            "barAlignment": 0,
            "barWidthFactor": 0.6,
            "drawStyle": "line",
            "fillOpacity": 0,
            "gradientMode": "none",
            "hideFrom": {
              "legend": false,
              "tooltip": false,
              "viz": false
            },
            "insertNulls": false,
            "lineInterpolation": "linear",
            "lineWidth": 1,
            "pointSize": 5,
            "scaleDistribution": {
              "type": "linear"
            },
            "showPoints": "never",
            "showValues": false,
            "spanNulls": false,
            "stacking": {
              "group": "A",
              "mode": "none"
            },
            "thresholdsStyle": {
              "mode": "off"
            }
          },
          "decimals": 1,
          "mappings": [],
          "thresholds": {
            "mode": "absolute",
            "steps": [
              {
                "color": "green",
                "value": 0
              }
            ]
          },
          "unit": "none"
        },
        "overrides": []
      },
      "gridPos": {
        "h": 6,
        "w": 6,
        "x": 6,
        "y": 30
      },
      "id": 23,
      "options": {
        "legend": {
          "calcs": [],
          "displayMode": "list",
          "placement": "bottom",
          "showLegend": true
        },
        "tooltip": {
          "hideZeros": true,
          "mode": "multi",
          "sort": "none"
        }
      },
      "pluginVersion": "12.3.0-18356121373.patch15",
      "targets": [
        {
          "editorMode": "code",
          "expr": "irate(system_network_dropped_total{host_name=\"$host_name\",direction=\"receive\",device!~\"lo|ovs-system\"}[$__rate_interval])",
          "legendFormat": "{{device}}",
          "range": true,
          "refId": "A",
          "datasource": {
            "type": "prometheus",
            "uid": "${DS_GRAFANACLOUD-RGORDILL-PROM}"
          }
        }
      ],
      "title": "Packet Receive Dropped",
      "type": "timeseries"
    },
    {
      "datasource": {
        "type": "prometheus",
        "uid": "${DS_GRAFANACLOUD-RGORDILL-PROM}"
      },
      "fieldConfig": {
        "defaults": {
          "color": {
            "mode": "palette-classic"
          },
          "custom": {
            "axisBorderShow": false,
            "axisCenteredZero": false,
            "axisColorMode": "text",
            "axisLabel": "",
            "axisPlacement": "auto",
            "barAlignment": 0,
            "barWidthFactor": 0.6,
            "drawStyle": "line",
            "fillOpacity": 0,
            "gradientMode": "none",
            "hideFrom": {
              "legend": false,
              "tooltip": false,
              "viz": false
            },
            "insertNulls": false,
            "lineInterpolation": "linear",
            "lineWidth": 1,
            "pointSize": 5,
            "scaleDistribution": {
              "type": "linear"
            },
            "showPoints": "never",
            "showValues": false,
            "spanNulls": false,
            "stacking": {
              "group": "A",
              "mode": "none"
            },
            "thresholdsStyle": {
              "mode": "off"
            }
          },
          "decimals": 1,
          "mappings": [],
          "thresholds": {
            "mode": "absolute",
            "steps": [
              {
                "color": "green",
                "value": 0
              }
            ]
          },
          "unit": "none"
        },
        "overrides": []
      },
      "gridPos": {
        "h": 6,
        "w": 6,
        "x": 12,
        "y": 30
      },
      "id": 22,
      "options": {
        "legend": {
          "calcs": [],
          "displayMode": "list",
          "placement": "bottom",
          "showLegend": true
        },
        "tooltip": {
          "hideZeros": true,
          "mode": "multi",
          "sort": "none"
        }
      },
      "pluginVersion": "12.3.0-18356121373.patch15",
      "targets": [
        {
          "editorMode": "code",
          "expr": "irate(system_network_errors_total{host_name=\"$host_name\",direction=\"transmit\",device!~\"lo|ovs-system\"}[$__rate_interval])",
          "legendFormat": "{{device}}",
          "range": true,
          "refId": "A",
          "datasource": {
            "type": "prometheus",
            "uid": "${DS_GRAFANACLOUD-RGORDILL-PROM}"
          }
        }
      ],
      "title": "Packet Transmit Error",
      "type": "timeseries"
    },
    {
      "datasource": {
        "type": "prometheus",
        "uid": "${DS_GRAFANACLOUD-RGORDILL-PROM}"
      },
      "fieldConfig": {
        "defaults": {
          "color": {
            "mode": "palette-classic"
          },
          "custom": {
            "axisBorderShow": false,
            "axisCenteredZero": false,
            "axisColorMode": "text",
            "axisLabel": "",
            "axisPlacement": "auto",
            "barAlignment": 0,
            "barWidthFactor": 0.6,
            "drawStyle": "line",
            "fillOpacity": 0,
            "gradientMode": "none",
            "hideFrom": {
              "legend": false,
              "tooltip": false,
              "viz": false
            },
            "insertNulls": false,
            "lineInterpolation": "linear",
            "lineWidth": 1,
            "pointSize": 5,
            "scaleDistribution": {
              "type": "linear"
            },
            "showPoints": "never",
            "showValues": false,
            "spanNulls": false,
            "stacking": {
              "group": "A",
              "mode": "none"
            },
            "thresholdsStyle": {
              "mode": "off"
            }
          },
          "decimals": 1,
          "mappings": [],
          "thresholds": {
            "mode": "absolute",
            "steps": [
              {
                "color": "green",
                "value": 0
              }
            ]
          },
          "unit": "none"
        },
        "overrides": []
      },
      "gridPos": {
        "h": 6,
        "w": 6,
        "x": 18,
        "y": 30
      },
      "id": 21,
      "options": {
        "legend": {
          "calcs": [],
          "displayMode": "list",
          "placement": "bottom",
          "showLegend": true
        },
        "tooltip": {
          "hideZeros": true,
          "mode": "multi",
          "sort": "none"
        }
      },
      "pluginVersion": "12.3.0-18356121373.patch15",
      "targets": [
        {
          "editorMode": "code",
          "expr": "irate(system_network_errors_total{host_name=\"$host_name\",direction=\"receive\",device!~\"lo|ovs-system\"}[$__rate_interval])",
          "legendFormat": "{{device}}",
          "range": true,
          "refId": "A",
          "datasource": {
            "type": "prometheus",
            "uid": "${DS_GRAFANACLOUD-RGORDILL-PROM}"
          }
        }
      ],
      "title": "Packet Receive Errors",
      "type": "timeseries"
    },
    {
      "collapsed": false,
      "gridPos": {
        "h": 1,
        "w": 24,
        "x": 0,
        "y": 36
      },
      "id": 25,
      "panels": [],
      "title": "Disk",
      "type": "row"
    },
    {
      "datasource": {
        "type": "prometheus",
        "uid": "${DS_GRAFANACLOUD-RGORDILL-PROM}"
      },
      "fieldConfig": {
        "defaults": {
          "color": {
            "mode": "palette-classic"
          },
          "custom": {
            "axisBorderShow": false,
            "axisCenteredZero": false,
            "axisColorMode": "text",
            "axisLabel": "",
            "axisPlacement": "auto",
            "barAlignment": 0,
            "barWidthFactor": 0.6,
            "drawStyle": "line",
            "fillOpacity": 0,
            "gradientMode": "none",
            "hideFrom": {
              "legend": false,
              "tooltip": false,
              "viz": false
            },
            "insertNulls": false,
            "lineInterpolation": "linear",
            "lineWidth": 1,
            "pointSize": 5,
            "scaleDistribution": {
              "type": "linear"
            },
            "showPoints": "never",
            "showValues": false,
            "spanNulls": false,
            "stacking": {
              "group": "A",
              "mode": "none"
            },
            "thresholdsStyle": {
              "mode": "off"
            }
          },
          "decimals": 1,
          "mappings": [],
          "thresholds": {
            "mode": "absolute",
            "steps": [
              {
                "color": "green",
                "value": 0
              }
            ]
          },
          "unit": "bytes"
        },
        "overrides": []
      },
      "gridPos": {
        "h": 6,
        "w": 6,
        "x": 0,
        "y": 37
      },
      "id": 26,
      "options": {
        "legend": {
          "calcs": [],
          "displayMode": "list",
          "placement": "bottom",
          "showLegend": true
        },
        "tooltip": {
          "hideZeros": true,
          "mode": "multi",
          "sort": "none"
        }
      },
      "pluginVersion": "12.3.0-18356121373.patch15",
      "targets": [
        {
          "editorMode": "code",
          "expr": "irate(system_disk_io_bytes_total{host_name=\"$host_name\",direction=\"read\",device!~\".*[0-9]\"}[$__rate_interval])",
          "legendFormat": "{{device}}",
          "range": true,
          "refId": "A",
          "datasource": {
            "type": "prometheus",
            "uid": "${DS_GRAFANACLOUD-RGORDILL-PROM}"
          }
        }
      ],
      "title": "Bytes Read",
      "type": "timeseries"
    },
    {
      "datasource": {
        "type": "prometheus",
        "uid": "${DS_GRAFANACLOUD-RGORDILL-PROM}"
      },
      "fieldConfig": {
        "defaults": {
          "color": {
            "mode": "palette-classic"
          },
          "custom": {
            "axisBorderShow": false,
            "axisCenteredZero": false,
            "axisColorMode": "text",
            "axisLabel": "",
            "axisPlacement": "auto",
            "barAlignment": 0,
            "barWidthFactor": 0.6,
            "drawStyle": "line",
            "fillOpacity": 0,
            "gradientMode": "none",
            "hideFrom": {
              "legend": false,
              "tooltip": false,
              "viz": false
            },
            "insertNulls": false,
            "lineInterpolation": "linear",
            "lineWidth": 1,
            "pointSize": 5,
            "scaleDistribution": {
              "type": "linear"
            },
            "showPoints": "never",
            "showValues": false,
            "spanNulls": false,
            "stacking": {
              "group": "A",
              "mode": "none"
            },
            "thresholdsStyle": {
              "mode": "off"
            }
          },
          "decimals": 1,
          "mappings": [],
          "thresholds": {
            "mode": "absolute",
            "steps": [
              {
                "color": "green",
                "value": 0
              }
            ]
          },
          "unit": "bytes"
        },
        "overrides": []
      },
      "gridPos": {
        "h": 6,
        "w": 6,
        "x": 6,
        "y": 37
      },
      "id": 27,
      "options": {
        "legend": {
          "calcs": [],
          "displayMode": "list",
          "placement": "bottom",
          "showLegend": true
        },
        "tooltip": {
          "hideZeros": true,
          "mode": "multi",
          "sort": "none"
        }
      },
      "pluginVersion": "12.3.0-18356121373.patch15",
      "targets": [
        {
          "editorMode": "code",
          "expr": "irate(system_disk_io_bytes_total{host_name=\"$host_name\",direction=\"write\",device!~\".*[0-9]\"}[$__rate_interval])",
          "legendFormat": "{{device}}",
          "range": true,
          "refId": "A",
          "datasource": {
            "type": "prometheus",
            "uid": "${DS_GRAFANACLOUD-RGORDILL-PROM}"
          }
        }
      ],
      "title": "Bytes Write",
      "type": "timeseries"
    },
    {
      "datasource": {
        "type": "prometheus",
        "uid": "${DS_GRAFANACLOUD-RGORDILL-PROM}"
      },
      "fieldConfig": {
        "defaults": {
          "color": {
            "mode": "palette-classic"
          },
          "custom": {
            "axisBorderShow": false,
            "axisCenteredZero": false,
            "axisColorMode": "text",
            "axisLabel": "",
            "axisPlacement": "auto",
            "barAlignment": 0,
            "barWidthFactor": 0.6,
            "drawStyle": "line",
            "fillOpacity": 0,
            "gradientMode": "none",
            "hideFrom": {
              "legend": false,
              "tooltip": false,
              "viz": false
            },
            "insertNulls": false,
            "lineInterpolation": "linear",
            "lineWidth": 1,
            "pointSize": 5,
            "scaleDistribution": {
              "type": "linear"
            },
            "showPoints": "never",
            "showValues": false,
            "spanNulls": false,
            "stacking": {
              "group": "A",
              "mode": "none"
            },
            "thresholdsStyle": {
              "mode": "off"
            }
          },
          "decimals": 1,
          "mappings": [],
          "thresholds": {
            "mode": "absolute",
            "steps": [
              {
                "color": "green",
                "value": 0
              }
            ]
          },
          "unit": "none"
        },
        "overrides": []
      },
      "gridPos": {
        "h": 6,
        "w": 6,
        "x": 12,
        "y": 37
      },
      "id": 30,
      "options": {
        "legend": {
          "calcs": [],
          "displayMode": "list",
          "placement": "bottom",
          "showLegend": true
        },
        "tooltip": {
          "hideZeros": true,
          "mode": "multi",
          "sort": "none"
        }
      },
      "pluginVersion": "12.3.0-18356121373.patch15",
      "targets": [
        {
          "editorMode": "code",
          "expr": "irate(system_disk_operations_total{host_name=\"$host_name\",direction=\"read\",device!~\".*[0-9]\"}[$__rate_interval])",
          "legendFormat": "{{device}}",
          "range": true,
          "refId": "A",
          "datasource": {
            "type": "prometheus",
            "uid": "${DS_GRAFANACLOUD-RGORDILL-PROM}"
          }
        }
      ],
      "title": "Operations Read",
      "type": "timeseries"
    },
    {
      "datasource": {
        "type": "prometheus",
        "uid": "${DS_GRAFANACLOUD-RGORDILL-PROM}"
      },
      "fieldConfig": {
        "defaults": {
          "color": {
            "mode": "palette-classic"
          },
          "custom": {
            "axisBorderShow": false,
            "axisCenteredZero": false,
            "axisColorMode": "text",
            "axisLabel": "",
            "axisPlacement": "auto",
            "barAlignment": 0,
            "barWidthFactor": 0.6,
            "drawStyle": "line",
            "fillOpacity": 0,
            "gradientMode": "none",
            "hideFrom": {
              "legend": false,
              "tooltip": false,
              "viz": false
            },
            "insertNulls": false,
            "lineInterpolation": "linear",
            "lineWidth": 1,
            "pointSize": 5,
            "scaleDistribution": {
              "type": "linear"
            },
            "showPoints": "never",
            "showValues": false,
            "spanNulls": false,
            "stacking": {
              "group": "A",
              "mode": "none"
            },
            "thresholdsStyle": {
              "mode": "off"
            }
          },
          "decimals": 1,
          "mappings": [],
          "thresholds": {
            "mode": "absolute",
            "steps": [
              {
                "color": "green",
                "value": 0
              }
            ]
          },
          "unit": "none"
        },
        "overrides": []
      },
      "gridPos": {
        "h": 6,
        "w": 6,
        "x": 18,
        "y": 37
      },
      "id": 31,
      "options": {
        "legend": {
          "calcs": [],
          "displayMode": "list",
          "placement": "bottom",
          "showLegend": true
        },
        "tooltip": {
          "hideZeros": true,
          "mode": "multi",
          "sort": "none"
        }
      },
      "pluginVersion": "12.3.0-18356121373.patch15",
      "targets": [
        {
          "editorMode": "code",
          "expr": "irate(system_disk_operations_total{host_name=\"$host_name\",direction=\"write\",device!~\".*[0-9]\"}[$__rate_interval])",
          "legendFormat": "{{device}}",
          "range": true,
          "refId": "A",
          "datasource": {
            "type": "prometheus",
            "uid": "${DS_GRAFANACLOUD-RGORDILL-PROM}"
          }
        }
      ],
      "title": "Operations Write",
      "transparent": true,
      "type": "timeseries"
    },
    {
      "datasource": {
        "type": "prometheus",
        "uid": "${DS_GRAFANACLOUD-RGORDILL-PROM}"
      },
      "fieldConfig": {
        "defaults": {
          "color": {
            "mode": "palette-classic"
          },
          "custom": {
            "axisBorderShow": false,
            "axisCenteredZero": false,
            "axisColorMode": "text",
            "axisLabel": "",
            "axisPlacement": "auto",
            "barAlignment": 0,
            "barWidthFactor": 0.6,
            "drawStyle": "line",
            "fillOpacity": 0,
            "gradientMode": "none",
            "hideFrom": {
              "legend": false,
              "tooltip": false,
              "viz": false
            },
            "insertNulls": false,
            "lineInterpolation": "linear",
            "lineWidth": 1,
            "pointSize": 5,
            "scaleDistribution": {
              "type": "linear"
            },
            "showPoints": "never",
            "showValues": false,
            "spanNulls": false,
            "stacking": {
              "group": "A",
              "mode": "none"
            },
            "thresholdsStyle": {
              "mode": "off"
            }
          },
          "decimals": 1,
          "mappings": [],
          "thresholds": {
            "mode": "absolute",
            "steps": [
              {
                "color": "green",
                "value": 0
              }
            ]
          },
          "unit": "s"
        },
        "overrides": []
      },
      "gridPos": {
        "h": 6,
        "w": 8,
        "x": 0,
        "y": 43
      },
      "id": 34,
      "options": {
        "legend": {
          "calcs": [],
          "displayMode": "list",
          "placement": "bottom",
          "showLegend": true
        },
        "tooltip": {
          "hideZeros": true,
          "mode": "multi",
          "sort": "none"
        }
      },
      "pluginVersion": "12.3.0-18356121373.patch15",
      "targets": [
        {
          "editorMode": "code",
          "expr": "irate(system_disk_operation_time_seconds_total{host_name=\"$host_name\",direction=\"read\",device!~\".*[0-9]\"}[$__rate_interval])",
          "legendFormat": "{{device}}",
          "range": true,
          "refId": "A",
          "datasource": {
            "type": "prometheus",
            "uid": "${DS_GRAFANACLOUD-RGORDILL-PROM}"
          }
        }
      ],
      "title": "Operations Read Time",
      "type": "timeseries"
    },
    {
      "datasource": {
        "type": "prometheus",
        "uid": "${DS_GRAFANACLOUD-RGORDILL-PROM}"
      },
      "fieldConfig": {
        "defaults": {
          "color": {
            "mode": "palette-classic"
          },
          "custom": {
            "axisBorderShow": false,
            "axisCenteredZero": false,
            "axisColorMode": "text",
            "axisLabel": "",
            "axisPlacement": "auto",
            "barAlignment": 0,
            "barWidthFactor": 0.6,
            "drawStyle": "line",
            "fillOpacity": 0,
            "gradientMode": "none",
            "hideFrom": {
              "legend": false,
              "tooltip": false,
              "viz": false
            },
            "insertNulls": false,
            "lineInterpolation": "linear",
            "lineWidth": 1,
            "pointSize": 5,
            "scaleDistribution": {
              "type": "linear"
            },
            "showPoints": "never",
            "showValues": false,
            "spanNulls": false,
            "stacking": {
              "group": "A",
              "mode": "none"
            },
            "thresholdsStyle": {
              "mode": "off"
            }
          },
          "decimals": 1,
          "mappings": [],
          "thresholds": {
            "mode": "absolute",
            "steps": [
              {
                "color": "green",
                "value": 0
              }
            ]
          },
          "unit": "s"
        },
        "overrides": []
      },
      "gridPos": {
        "h": 6,
        "w": 8,
        "x": 8,
        "y": 43
      },
      "id": 33,
      "options": {
        "legend": {
          "calcs": [],
          "displayMode": "list",
          "placement": "bottom",
          "showLegend": true
        },
        "tooltip": {
          "hideZeros": true,
          "mode": "multi",
          "sort": "none"
        }
      },
      "pluginVersion": "12.3.0-18356121373.patch15",
      "targets": [
        {
          "editorMode": "code",
          "expr": "irate(system_disk_operation_time_seconds_total{host_name=\"$host_name\",direction=\"write\",device!~\".*[0-9]\"}[$__rate_interval])",
          "legendFormat": "{{device}}",
          "range": true,
          "refId": "A",
          "datasource": {
            "type": "prometheus",
            "uid": "${DS_GRAFANACLOUD-RGORDILL-PROM}"
          }
        }
      ],
      "title": "Operations Write Time",
      "type": "timeseries"
    },
    {
      "datasource": {
        "type": "prometheus",
        "uid": "${DS_GRAFANACLOUD-RGORDILL-PROM}"
      },
      "fieldConfig": {
        "defaults": {
          "color": {
            "mode": "palette-classic"
          },
          "custom": {
            "axisBorderShow": false,
            "axisCenteredZero": false,
            "axisColorMode": "text",
            "axisLabel": "",
            "axisPlacement": "auto",
            "barAlignment": 0,
            "barWidthFactor": 0.6,
            "drawStyle": "line",
            "fillOpacity": 0,
            "gradientMode": "none",
            "hideFrom": {
              "legend": false,
              "tooltip": false,
              "viz": false
            },
            "insertNulls": false,
            "lineInterpolation": "linear",
            "lineWidth": 1,
            "pointSize": 5,
            "scaleDistribution": {
              "type": "linear"
            },
            "showPoints": "never",
            "showValues": false,
            "spanNulls": false,
            "stacking": {
              "group": "A",
              "mode": "none"
            },
            "thresholdsStyle": {
              "mode": "off"
            }
          },
          "decimals": 1,
          "mappings": [],
          "thresholds": {
            "mode": "absolute",
            "steps": [
              {
                "color": "green",
                "value": 0
              }
            ]
          },
          "unit": "s"
        },
        "overrides": []
      },
      "gridPos": {
        "h": 6,
        "w": 8,
        "x": 16,
        "y": 43
      },
      "id": 28,
      "options": {
        "legend": {
          "calcs": [],
          "displayMode": "list",
          "placement": "bottom",
          "showLegend": true
        },
        "tooltip": {
          "hideZeros": true,
          "mode": "multi",
          "sort": "none"
        }
      },
      "pluginVersion": "12.3.0-18356121373.patch15",
      "targets": [
        {
          "editorMode": "code",
          "expr": "irate(system_disk_io_time_seconds_total{host_name=\"$host_name\",device!~\".*[0-9]\"}[$__rate_interval])",
          "legendFormat": "{{device}}",
          "range": true,
          "refId": "A",
          "datasource": {
            "type": "prometheus",
            "uid": "${DS_GRAFANACLOUD-RGORDILL-PROM}"
          }
        }
      ],
      "title": "IO Time",
      "type": "timeseries"
    },
    {
      "datasource": {
        "type": "prometheus",
        "uid": "${DS_GRAFANACLOUD-RGORDILL-PROM}"
      },
      "fieldConfig": {
        "defaults": {
          "color": {
            "mode": "palette-classic"
          },
          "custom": {
            "axisBorderShow": false,
            "axisCenteredZero": false,
            "axisColorMode": "text",
            "axisLabel": "",
            "axisPlacement": "auto",
            "barAlignment": 0,
            "barWidthFactor": 0.6,
            "drawStyle": "line",
            "fillOpacity": 0,
            "gradientMode": "none",
            "hideFrom": {
              "legend": false,
              "tooltip": false,
              "viz": false
            },
            "insertNulls": false,
            "lineInterpolation": "linear",
            "lineWidth": 1,
            "pointSize": 5,
            "scaleDistribution": {
              "type": "linear"
            },
            "showPoints": "never",
            "showValues": false,
            "spanNulls": false,
            "stacking": {
              "group": "A",
              "mode": "none"
            },
            "thresholdsStyle": {
              "mode": "off"
            }
          },
          "decimals": 1,
          "mappings": [],
          "thresholds": {
            "mode": "absolute",
            "steps": [
              {
                "color": "green",
                "value": 0
              }
            ]
          },
          "unit": "none"
        },
        "overrides": [
          {
            "__systemRef": "hideSeriesFrom",
            "matcher": {
              "id": "byNames",
              "options": {
                "mode": "exclude",
                "names": [
                  "vda"
                ],
                "prefix": "All except:",
                "readOnly": true
              }
            },
            "properties": [
              {
                "id": "custom.hideFrom",
                "value": {
                  "legend": false,
                  "tooltip": true,
                  "viz": true
                }
              }
            ]
          }
        ]
      },
      "gridPos": {
        "h": 6,
        "w": 12,
        "x": 0,
        "y": 49
      },
      "id": 29,
      "options": {
        "legend": {
          "calcs": [],
          "displayMode": "list",
          "placement": "bottom",
          "showLegend": true
        },
        "tooltip": {
          "hideZeros": false,
          "mode": "multi",
          "sort": "none"
        }
      },
      "pluginVersion": "12.3.0-18356121373.patch15",
      "targets": [
        {
          "editorMode": "code",
          "expr": "(\n  irate(system_disk_weighted_io_time_seconds_total{host_name=\"$host_name\",device!~\".*[0-9]\"}[$__rate_interval])\n  /\n  irate(system_disk_io_time_seconds_total{host_name=\"$host_name\",device!~\".*[0-9]\"}[$__rate_interval])\n)",
          "legendFormat": "{{device}}",
          "range": true,
          "refId": "A",
          "datasource": {
            "type": "prometheus",
            "uid": "${DS_GRAFANACLOUD-RGORDILL-PROM}"
          }
        }
      ],
      "title": "Queue Length",
      "type": "timeseries"
    },
    {
      "datasource": {
        "type": "prometheus",
        "uid": "${DS_GRAFANACLOUD-RGORDILL-PROM}"
      },
      "fieldConfig": {
        "defaults": {
          "color": {
            "mode": "palette-classic"
          },
          "custom": {
            "axisBorderShow": false,
            "axisCenteredZero": false,
            "axisColorMode": "text",
            "axisLabel": "",
            "axisPlacement": "auto",
            "barAlignment": 0,
            "barWidthFactor": 0.6,
            "drawStyle": "line",
            "fillOpacity": 0,
            "gradientMode": "none",
            "hideFrom": {
              "legend": false,
              "tooltip": false,
              "viz": false
            },
            "insertNulls": false,
            "lineInterpolation": "linear",
            "lineWidth": 1,
            "pointSize": 5,
            "scaleDistribution": {
              "type": "linear"
            },
            "showPoints": "never",
            "showValues": false,
            "spanNulls": false,
            "stacking": {
              "group": "A",
              "mode": "none"
            },
            "thresholdsStyle": {
              "mode": "off"
            }
          },
          "decimals": 1,
          "mappings": [],
          "thresholds": {
            "mode": "absolute",
            "steps": [
              {
                "color": "green",
                "value": 0
              }
            ]
          },
          "unit": "none"
        },
        "overrides": []
      },
      "gridPos": {
        "h": 6,
        "w": 12,
        "x": 12,
        "y": 49
      },
      "id": 32,
      "options": {
        "legend": {
          "calcs": [],
          "displayMode": "list",
          "placement": "bottom",
          "showLegend": true
        },
        "tooltip": {
          "hideZeros": true,
          "mode": "multi",
          "sort": "none"
        }
      },
      "pluginVersion": "12.3.0-18356121373.patch15",
      "targets": [
        {
          "editorMode": "code",
          "expr": "system_disk_pending_operations{host_name=\"$host_name\",device!~\".*[0-9]\"}",
          "legendFormat": "{{device}}",
          "range": true,
          "refId": "A",
          "datasource": {
            "type": "prometheus",
            "uid": "${DS_GRAFANACLOUD-RGORDILL-PROM}"
          }
        }
      ],
      "title": "Operations Pending",
      "type": "timeseries"
    },
    {
      "collapsed": false,
      "gridPos": {
        "h": 1,
        "w": 24,
        "x": 0,
        "y": 55
      },
      "id": 35,
      "panels": [],
      "title": "Filesystem",
      "type": "row"
    },
    {
      "datasource": {
        "type": "prometheus",
        "uid": "${DS_GRAFANACLOUD-RGORDILL-PROM}"
      },
      "fieldConfig": {
        "defaults": {
          "color": {
            "fixedColor": "dark-orange",
            "mode": "thresholds"
          },
          "custom": {
            "axisBorderShow": false,
            "axisCenteredZero": false,
            "axisColorMode": "text",
            "axisLabel": "",
            "axisPlacement": "auto",
            "barAlignment": 0,
            "barWidthFactor": 0.6,
            "drawStyle": "line",
            "fillOpacity": 0,
            "gradientMode": "none",
            "hideFrom": {
              "legend": false,
              "tooltip": false,
              "viz": false
            },
            "insertNulls": false,
            "lineInterpolation": "linear",
            "lineStyle": {
              "fill": "solid"
            },
            "lineWidth": 1,
            "pointSize": 5,
            "scaleDistribution": {
              "type": "linear"
            },
            "showPoints": "never",
            "showValues": false,
            "spanNulls": false,
            "stacking": {
              "group": "A",
              "mode": "none"
            },
            "thresholdsStyle": {
              "mode": "area"
            }
          },
          "mappings": [],
          "min": 6,
          "thresholds": {
            "mode": "percentage",
            "steps": [
              {
                "color": "dark-green",
                "value": 0
              },
              {
                "color": "dark-yellow",
                "value": 80
              },
              {
                "color": "dark-red",
                "value": 90
              }
            ]
          },
          "unit": "bytes"
        },
        "overrides": []
      },
      "gridPos": {
        "h": 10,
        "w": 24,
        "x": 0,
        "y": 56
      },
      "id": 36,
      "options": {
        "legend": {
          "calcs": [],
          "displayMode": "list",
          "placement": "bottom",
          "showLegend": true
        },
        "tooltip": {
          "hideZeros": false,
          "mode": "single",
          "sort": "none"
        }
      },
      "pluginVersion": "12.3.0-18356121373.patch15",
      "repeat": "mountpoint",
      "repeatDirection": "h",
      "targets": [
        {
          "editorMode": "code",
          "expr": "system_filesystem_usage_bytes{host_name=\"microshift\",state=\"used\",mountpoint=\"$mountpoint\"}",
          "legendFormat": "{{state}}",
          "range": true,
          "refId": "A",
          "datasource": {
            "type": "prometheus",
            "uid": "${DS_GRAFANACLOUD-RGORDILL-PROM}"
          }
        },
        {
          "datasource": {
            "type": "prometheus",
            "uid": "${DS_GRAFANACLOUD-RGORDILL-PROM}"
          },
          "editorMode": "code",
          "expr": "sum(system_filesystem_usage_bytes{host_name=\"microshift\",mountpoint=\"$mountpoint\"})",
          "hide": false,
          "instant": false,
          "legendFormat": "total",
          "range": true,
          "refId": "D"
        }
      ],
      "title": "Filesystem Usage ($mountpoint)",
      "transformations": [
        {
          "id": "configFromData",
          "options": {
            "configRefId": "D",
            "mappings": [
              {
                "fieldName": "total",
                "handlerKey": "max"
              }
            ]
          }
        }
      ],
      "type": "timeseries"
    },
    {
      "collapsed": false,
      "gridPos": {
        "h": 1,
        "w": 24,
        "x": 0,
        "y": 66
      },
      "id": 37,
      "panels": [],
      "title": "Processes",
      "type": "row"
    },
    {
      "datasource": {
        "type": "prometheus",
        "uid": "${DS_GRAFANACLOUD-RGORDILL-PROM}"
      },
      "fieldConfig": {
        "defaults": {
          "color": {
            "mode": "palette-classic"
          },
          "custom": {
            "axisBorderShow": false,
            "axisCenteredZero": false,
            "axisColorMode": "text",
            "axisLabel": "",
            "axisPlacement": "auto",
            "barAlignment": 0,
            "barWidthFactor": 0.6,
            "drawStyle": "line",
            "fillOpacity": 0,
            "gradientMode": "none",
            "hideFrom": {
              "legend": false,
              "tooltip": false,
              "viz": false
            },
            "insertNulls": false,
            "lineInterpolation": "linear",
            "lineWidth": 1,
            "pointSize": 5,
            "scaleDistribution": {
              "type": "linear"
            },
            "showPoints": "never",
            "showValues": false,
            "spanNulls": false,
            "stacking": {
              "group": "A",
              "mode": "none"
            },
            "thresholdsStyle": {
              "mode": "off"
            }
          },
          "decimals": 1,
          "mappings": [],
          "thresholds": {
            "mode": "absolute",
            "steps": [
              {
                "color": "green",
                "value": 0
              }
            ]
          }
        },
        "overrides": []
      },
      "gridPos": {
        "h": 6,
        "w": 12,
        "x": 0,
        "y": 67
      },
      "id": 38,
      "options": {
        "legend": {
          "calcs": [],
          "displayMode": "list",
          "placement": "bottom",
          "showLegend": true
        },
        "tooltip": {
          "hideZeros": true,
          "mode": "multi",
          "sort": "none"
        }
      },
      "pluginVersion": "12.3.0-18356121373.patch15",
      "targets": [
        {
          "editorMode": "code",
          "expr": "system_processes_count{host_name=\"$host_name\"}",
          "legendFormat": "{{status}}",
          "range": true,
          "refId": "A",
          "datasource": {
            "type": "prometheus",
            "uid": "${DS_GRAFANACLOUD-RGORDILL-PROM}"
          }
        }
      ],
      "title": "Processes",
      "type": "timeseries"
    },
    {
      "datasource": {
        "type": "prometheus",
        "uid": "${DS_GRAFANACLOUD-RGORDILL-PROM}"
      },
      "fieldConfig": {
        "defaults": {
          "color": {
            "mode": "palette-classic"
          },
          "custom": {
            "axisBorderShow": false,
            "axisCenteredZero": false,
            "axisColorMode": "text",
            "axisLabel": "",
            "axisPlacement": "auto",
            "barAlignment": 0,
            "barWidthFactor": 0.6,
            "drawStyle": "line",
            "fillOpacity": 0,
            "gradientMode": "none",
            "hideFrom": {
              "legend": false,
              "tooltip": false,
              "viz": false
            },
            "insertNulls": false,
            "lineInterpolation": "linear",
            "lineWidth": 1,
            "pointSize": 5,
            "scaleDistribution": {
              "type": "linear"
            },
            "showPoints": "never",
            "showValues": false,
            "spanNulls": false,
            "stacking": {
              "group": "A",
              "mode": "none"
            },
            "thresholdsStyle": {
              "mode": "off"
            }
          },
          "decimals": 1,
          "mappings": [],
          "thresholds": {
            "mode": "absolute",
            "steps": [
              {
                "color": "green",
                "value": 0
              }
            ]
          }
        },
        "overrides": []
      },
      "gridPos": {
        "h": 6,
        "w": 12,
        "x": 12,
        "y": 67
      },
      "id": 39,
      "options": {
        "legend": {
          "calcs": [],
          "displayMode": "list",
          "placement": "bottom",
          "showLegend": true
        },
        "tooltip": {
          "hideZeros": true,
          "mode": "multi",
          "sort": "none"
        }
      },
      "pluginVersion": "12.3.0-18356121373.patch15",
      "targets": [
        {
          "editorMode": "code",
          "expr": "irate(system_processes_created_total{host_name=\"$host_name\"}[$__rate_interval])",
          "legendFormat": "new",
          "range": true,
          "refId": "A",
          "datasource": {
            "type": "prometheus",
            "uid": "${DS_GRAFANACLOUD-RGORDILL-PROM}"
          }
        }
      ],
      "title": "Process Creation",
      "type": "timeseries"
    }
  ],
  "refresh": "30s",
  "schemaVersion": 42,
  "tags": [
    "linux",
    "otelcol-contrib",
    "opentelemetry"
  ],
  "templating": {
    "list": [
      {
        "current": {},
        "includeAll": false,
        "label": "datasource",
        "name": "DS_PROMETHEUS",
        "options": [],
        "query": "prometheus",
        "refresh": 1,
        "regex": "",
        "type": "datasource"
      },
      {
        "current": {},
        "datasource": {
          "type": "prometheus",
          "uid": "${DS_PROMETHEUS}"
        },
        "definition": "label_values(system_uptime_seconds,host_name)",
        "includeAll": false,
        "label": "host",
        "name": "host_name",
        "options": [],
        "query": {
          "qryType": 1,
          "query": "label_values(system_uptime_seconds,host_name)",
          "refId": "PrometheusVariableQueryEditor-VariableQuery"
        },
        "refresh": 1,
        "regex": "",
        "sort": 1,
        "type": "query"
      },
      {
        "allowCustomValue": false,
        "current": {},
        "datasource": {
          "type": "prometheus",
          "uid": "${DS_PROMETHEUS}"
        },
        "definition": "label_values(system_filesystem_usage_bytes{host_name=\"$host_name\"},mountpoint)",
        "hide": 2,
        "includeAll": true,
        "multi": true,
        "name": "mountpoint",
        "options": [],
        "query": {
          "qryType": 1,
          "query": "label_values(system_filesystem_usage_bytes{host_name=\"$host_name\"},mountpoint)",
          "refId": "PrometheusVariableQueryEditor-VariableQuery"
        },
        "refresh": 1,
        "regex": "",
        "type": "query"
      }
    ]
  },
  "time": {
    "from": "now-30m",
    "to": "now"
  },
  "timepicker": {},
  "timezone": "browser",
  "title": "HostMetrics",
  "uid": "otel-hostmetrics",
  "version": 85,
  "weekStart": ""
}